pydantic_rpc/__init__.py
pydantic_rpc/core.py
pydantic_rpc/decorators.py
pydantic_rpc/mcp/__init__.py
pydantic_rpc/mcp/converter.py
pydantic_rpc/mcp/exporter.py
pydantic_rpc/options.py
pydantic_rpc/py.typed
pydantic_rpc/tls.py
pydantic_rpc-0.15.1.dist-info/WHEEL
pydantic_rpc-0.15.1.dist-info/METADATA
pydantic_rpc-0.15.1.dist-info/RECORD
