Metadata-Version: 2.3
Name: pydantic-rpc
Version: 0.15.1
Summary: A Python library for building gRPC/ConnectRPC services with Pydantic models.
Author: Yasushi Itoh
Classifier: Programming Language :: Python :: 3.11
Classifier: Programming Language :: Python :: 3.12
Classifier: Programming Language :: Python :: 3.13
Classifier: Programming Language :: Python :: 3.14
Requires-Dist: annotated-types==0.7.0
Requires-Dist: pydantic>=2.1.1
Requires-Dist: grpcio>=1.56.2
Requires-Dist: grpcio-tools>=1.56.2
Requires-Dist: grpcio-reflection>=1.56.2
Requires-Dist: grpcio-health-checking>=1.56.2
Requires-Dist: connect-python>=0.5.0
Requires-Dist: protoc-gen-connect-python>=0.1.0
Requires-Dist: mcp>=1.9.4
Requires-Dist: starlette>=0.27.0
Requires-Python: >=3.11
